LICENSE.txt
MANIFEST.in
README.md
setup.py
persons/__init__.py
persons/persons.py
persons.egg-info/PKG-INFO
persons.egg-info/SOURCES.txt
persons.egg-info/dependency_links.txt
persons.egg-info/not-zip-safe
persons.egg-info/requires.txt
persons.egg-info/top_level.txt
persons/support_functions/__init__.py
persons/support_functions/graph_functions.py
persons/support_functions/string_tools.py