Metadata-Version: 1.0
Name: persons
Version: 0.2a0
Summary: Graph-based author disambiguation. Identifies distinct persons by matching forenames and surnames. Supports known persons, year data, and others.
Home-page: https://github.com/SaschaSchweitzer/persons
Author: Sascha Schweitzer
Author-email: sascha.schweitzer@gmail.com
License: Apache License, Version 2.0
Platform: UNKNOWN
